odoo10_addon_l10n_fr_department_delivery-10.0.0.1.0.99.dev3-py2.7-nspkg.pth
odoo/addons/l10n_fr_department_delivery/README.rst
odoo/addons/l10n_fr_department_delivery/__init__.py
odoo/addons/l10n_fr_department_delivery/__manifest__.py
odoo/addons/l10n_fr_department_delivery/i18n/l10n_fr_department_delivery.pot
odoo/addons/l10n_fr_department_delivery/models/__init__.py
odoo/addons/l10n_fr_department_delivery/models/delivery.py
odoo/addons/l10n_fr_department_delivery/static/description/icon.png
odoo/addons/l10n_fr_department_delivery/views/delivery.xml
odoo10_addon_l10n_fr_department_delivery-10.0.0.1.0.99.dev3.dist-info/METADATA
odoo10_addon_l10n_fr_department_delivery-10.0.0.1.0.99.dev3.dist-info/RECORD
odoo10_addon_l10n_fr_department_delivery-10.0.0.1.0.99.dev3.dist-info/WHEEL
odoo10_addon_l10n_fr_department_delivery-10.0.0.1.0.99.dev3.dist-info/namespace_packages.txt
odoo10_addon_l10n_fr_department_delivery-10.0.0.1.0.99.dev3.dist-info/top_level.txt
